autoxinit/autoxinit.py
autoxinit/__init__.py
autoxinit/test/testModule.py
autoxinit/test/testFunction.py
autoxinit/test/testClass.py
autoxinit/test/__init__.py
autoxinit-0.1.2.dist-info/RECORD
autoxinit-0.1.2.dist-info/METADATA
autoxinit-0.1.2.dist-info/WHEEL
autoxinit-0.1.2.dist-info/top_level.txt
autoxinit-0.1.2.dist-info/metadata.json
autoxinit-0.1.2.dist-info/DESCRIPTION.rst
