Metadata-Version: 2.0
Name: autoxinit
Version: 0.1.2
Summary: 
